ngocthanhcalculator/__init__.py
ngocthanhcalculator-0.1.dist-info/LICENSE.TXT
ngocthanhcalculator-0.1.dist-info/METADATA
ngocthanhcalculator-0.1.dist-info/WHEEL
ngocthanhcalculator-0.1.dist-info/top_level.txt
ngocthanhcalculator-0.1.dist-info/RECORD
