Metadata-Version: 2.1
Name: ngocthanhcalculator
Version: 0.1
Summary: This is demo python caculator package
Home-page: UNKNOWN
Author: Phạm Ngọc Thành
Author-email: phamngocthanh3009@gmail.com
License: UNKNOWN
Platform: UNKNOWN
Classifier: Programming Language :: Python :: 3
Classifier: License :: OSI Approved :: MIT License
Classifier: Operating System :: OS Independent
License-File: LICENSE.TXT
